{
  "coreVersion": 3,
  "ine": "\u5e73\u6c11\u641c\u7d22\u5217\u8868",
  "info": "",
  "inq": "\u5e73\u6c11\u5217\u8868",
  "ins": [],
  "mous": [
    {
      "attr": "{\"desc\":false,\"flow\":false,\"itemtarget\":\"\u64ad\u653e\u5668\",\"max\":0,\"row\":3,\"type\":5}",
      "host": {
        "a": "\u5e73\u6c11"
      },
      "ins": [
        {
          "a": "list",
          "s": [
            {
              "a": "list",
              "v": ".get(ul.col_3_1 div.movie-item)"
            },
            {
              "a": "name",
              "v": ".get(a.txtA).t()"
            },
            {
              "a": "url",
              "v": ".get(a.ImgA).a(href)"
            },
            {
              "a": "msg",
              "v": ".get(a.ImgA).t()"
            },
            {
              "a": "img",
              "v": ".get(a.ImgA img).a(src)"
            }
          ]
        }
      ],
      "ors": [
        {
          "a": "scr",
          "v": "[{\"a\":\"mtype\",\"s\":[{\"a\":\"\u7535\u5f71\",\"v\":\"1\"},{\"a\":\"\u7535\u89c6\u5267\",\"v\":\"2\"},{\"a\":\"\u7efc\u827a\",\"v\":\"3\"},{\"a\":\"\u52a8\u6f2b\",\"v\":\"4\"},{\"a\":\"\u4f26\u7406\",\"v\":\"22\"}]},{\"a\":\"mfilter\",\"s\":[{\"a\":\"\u6700\u65b0\",\"v\":\"time\"},{\"a\":\"\u4eba\u6c14\",\"v\":\"hits\"},{\"a\":\"\u597d\u8bc4\",\"v\":\"score\"}]}]"
        }
      ],
      "sign": "\u5e73\u6c11\u5217\u8868",
      "type": 1
    },
    {
      "attr": "{}",
      "host": {
        "a": "#\u53d6\u4e0a\u7ea7\u6e90\u7801"
      },
      "ins": [
        {
          "a": "list",
          "s": [
            {
              "a": "list",
              "v": ".get(ul li)"
            },
            {
              "a": "name",
              "v": ".get(a).t()"
            },
            {
              "a": "url",
              "v": ".get(a).a(href)"
            }
          ]
        }
      ],
      "sign": "\u9009\u96c6",
      "type": 2
    },
    {
      "attr": "{\"childmou\":\"\u9009\u96c6\"}",
      "host": {
        "a": "#\u53d6\u4e0a\u7ea7\u6e90\u7801"
      },
      "ins": [
        {
          "a": "a",
          "s": [
            {
              "a": "sort",
              "v": ".get(div.lhmain)"
            },
            {
              "a": "s_name",
              "v": ".get(p.laiyuan).t()"
            }
          ]
        }
      ],
      "sign": "\u9009\u96c6\u5217\u8868",
      "type": 5
    },
    {
      "attr": "{\"m_info\":\"\",\"m_list\":\"\u9009\u96c6\u5217\u8868\"}",
      "host": {
        "a": "#\u8bfb\u4e0a\u7ea7\u5730\u5740"
      },
      "ins": [
        {
          "a": "con",
          "s": [
            {
              "a": "playurl",
              "v": ""
            }
          ]
        }
      ],
      "sign": "\u64ad\u653e\u5668",
      "type": 11
    },
    {
      "attr": "{\"desc\":false,\"flow\":false,\"itemtarget\":\"\u64ad\u653e\u5668\",\"max\":0,\"row\":1,\"type\":1}",
      "host": {
        "a": "\u5e73\u6c11\u641c\u7d22"
      },
      "ins": [
        {
          "a": "list",
          "s": [
            {
              "a": "list",
              "v": ".get(ul#data_list li)"
            },
            {
              "a": "name",
              "v": ".get(p.sTit a).t()"
            },
            {
              "a": "url",
              "v": ".get(p.sTit a).a(href)"
            },
            {
              "a": "msg",
              "v": ".get(span.sBottom).t()"
            },
            {
              "a": "img",
              "v": ".get(a img).a(src)"
            }
          ]
        }
      ],
      "ors": [
        {
          "a": "scr",
          "v": "[]"
        }
      ],
      "sign": "\u5e73\u6c11\u641c\u7d22\u5217\u8868",
      "type": 1
    }
  ],
  "name": "\u5e73\u6c11\u5f71\u89c6",
  "sign": "8b9083d822fa74cfcb5b3b307b6957af",
  "sqlId": 57,
  "vars": [
    {
      "a": "#\u722c\u866b",
      "sign": "\u5e73\u6c11",
      "v": "{\"code\":\"\",\"mode\":0,\"pn_raise\":1,\"pn_start\":1,\"post\":\"\",\"ua\":\"\",\"url\":\"https://v.pmys6.com/index.php?m\\u003dvod-list-id-mtype-pg-%pn%-order--by-mfilter-class--year--letter--area--lang-.html\"}"
    },
    {
      "a": "#\u722c\u866b",
      "sign": "\u5e73\u6c11\u641c\u7d22",
      "v": "{\"code\":\"\",\"mode\":0,\"pn_raise\":1,\"pn_start\":1,\"post\":\"\",\"ua\":\"\",\"url\":\"https://v.pmys6.com/index.php?m\\u003dvod-search-pg-%pn%-wd-%key%.html\"}"
    }
  ],
  "version": 0
}